[
  {
    "mode": "REQUIRED",
    "name": "AuthorId",
    "type": "INTEGER"
  },
  {
    "mode": "NULLABLE",
    "name": "Rank",
    "type": "INTEGER"
  },
  {
    "mode": "NULLABLE",
    "name": "NormalizedName",
    "type": "STRING"
  },
  {
    "mode": "NULLABLE",
    "name": "DisplayName",
    "type": "STRING"
  },
  {
    "mode": "NULLABLE",
    "name": "LastKnownAffiliationId",
    "type": "INTEGER"
  },
  {
    "mode": "NULLABLE",
    "name": "PaperCount",
    "type": "INTEGER"
  },
  {
    "mode": "NULLABLE",
    "name": "PaperFamilyCount",
    "type": "Integer"
  },
  {
    "mode": "NULLABLE",
    "name": "CitationCount",
    "type": "INTEGER"
  },
  {
    "description": "%E4Y-%m-%d",
    "mode": "NULLABLE",
    "name": "CreateDate",
    "type": "DATE"
  }
]
